[
  {
    "TrueFactEnglish": "A blue whale calf can gain 8 pounds an hour during its first 7 months.",
    "TrueFactMandarin": "蓝鲸宝宝出生后首7个月，每8小时体重会增长4公斤。",
    "TrueFactSuggestedLineBreak": "蓝鲸宝宝出生后首7个月，\r每周体重会增长约2公斤。",
    "FalseFactEnglish": "A blue whale calf can gain 5 pounds a week it’s first 7 months",
    "FalseFactMandarin": "蓝鲸宝宝出生后首7个月，每周体重会增长约2公斤。",
    "TrueFactSpanish": "Una cría de ballena azul puede ganar 3.62 kilogramos por hora durante sus primeros 7 meses de vida.",
    "FalseFactSpanish": "Una cría de ballena azul puede ganar 2.2679 kilogramos por semana durante sus primeros 7 meses."
  },
  {
    "TrueFactEnglish": "A blue whale’s heart weighs up to a ton.",
    "TrueFactMandarin": "蓝鲸的心脏重达1000公斤。",
    "TrueFactSuggestedLineBreak": "蓝鲸的心脏\r比一头大象的心脏还要轻。",
    "FalseFactEnglish": "A blue whale’s heart is lighter than an elephant's.",
    "FalseFactMandarin": "蓝鲸的心脏比一头大象的心脏还要轻。",
    "TrueFactSpanish": "El corazón de una ballena azul pesa hasta 1000 kilos",
    "FalseFactSpanish": "El corazón de una ballena azul es más liviano que el de un elefante."
  },
  {
    "TrueFactEnglish": "A Cuttlefish’s pupils are shaped like W’s.",
    "TrueFactMandarin": "乌贼的瞳孔形状是“W”型的。",
    "TrueFactSuggestedLineBreak": "乌贼的瞳孔形状\r像阿拉伯数字“3”。",
    "FalseFactEnglish": "The Cuttlefish’s pupils are shaped like the number 3",
    "FalseFactMandarin": "乌贼的瞳孔形状像阿拉伯数字“3”。",
    "TrueFactSpanish": "Las pupilas de los peces sepias tienen forma de W.",
    "FalseFactSpanish": "Las pupilas de los peces sepia tienen la forma del número 3."
  },
  {
    "TrueFactEnglish": "A goblin shark can thrust its jaws out of its mouth.",
    "TrueFactMandarin": "欧氏尖吻鲛可将颚子伸出嘴巴。",
    "TrueFactSuggestedLineBreak": "欧氏尖吻鲛没有嘴巴，\r就跟蝴蝶一样。",
    "FalseFactEnglish": "Like a butterfly, a goblin shark doesn't have a mouth.",
    "FalseFactMandarin": "欧氏尖吻鲛没有嘴巴，就跟蝴蝶一样。",
    "TrueFactSpanish": "El tiburón duende puede expulsar sus mandíbulas fuera de la boca.",
    "FalseFactSpanish": "Al igual que las mariposas, el tiburón duende no tiene boca."
  },
  {
    "TrueFactEnglish": "A great white shark can weigh as much as 15 gorillas.",
    "TrueFactMandarin": "大白鲨可重达15只大猩猩。",
    "TrueFactSuggestedLineBreak": "大白鲨跟一只大猩猩一样重。",
    "FalseFactEnglish": "A great white shark can weigh as much a gorilla.",
    "FalseFactMandarin": "大白鲨跟一只大猩猩一样重。",
    "TrueFactSpanish": "Un tiburón blanco puede pesar tanto como 15 gorilas.",
    "FalseFactSpanish": "Un tiburón blanco puede pesar tanto como un gorila."
  },
  {
    "TrueFactEnglish": "A group of jellyfish is called a smack.",
    "TrueFactMandarin": "在英文里，“一群水母”可用“smack”作为量词。",
    "TrueFactSuggestedLineBreak": "在英文里，“一群水母”\r被称为“Grouplefish”。",
    "FalseFactEnglish": "A group of jellyfish is called a Grouplefish.",
    "FalseFactMandarin": "在英文里，“一群水母”被称为“Grouplefish”。",
    "TrueFactSpanish": "Un grupo de medusas se llama flor.",
    "FalseFactSpanish": "Un grupo de medusas se llama fiesta de peces"
  },
  {
    "TrueFactEnglish": "A jellyfish can be as small a thimble or as big two washing machines.",
    "TrueFactMandarin": "水母可以小得像一个顶针，也可以大得像两台洗衣机。",
    "TrueFactSuggestedLineBreak": "水母可以小得像一支针，\r也可以大得像两个火车厢。",
    "FalseFactEnglish": "A jellyfish can be as small a needle or as big two train cars.",
    "FalseFactMandarin": "水母可以小得像一支针，也可以大得像两个火车厢。",
    "TrueFactSpanish": "Una medusa puede ser tan pequeña como un dedal o tan grande como dos lavadoras.",
    "FalseFactSpanish": "Una medusa puede ser tan pequeña como una aguja o tan grande como dos vagones de tren."
  },
  {
    "TrueFactEnglish": "A lobster’s teeth are in its stomach.",
    "TrueFactMandarin": "龙虾的牙齿长在胃里。",
    "TrueFactSuggestedLineBreak": "龙虾的牙齿长在钳子上。",
    "FalseFactEnglish": "A lobster’s teeth are in it's claws.",
    "FalseFactMandarin": "龙虾的牙齿长在钳子上。",
    "TrueFactSpanish": "Los dientes de una langosta están en su estómago.",
    "FalseFactSpanish": "Los dientes de una langosta están en sus tenazas."
  },
  {
    "TrueFactEnglish": "A mass of floating ice that looks like an iceberg is called a floeberg.",
    "TrueFactMandarin": "在水面上漂浮的小冰山被称为浮冰丘。",
    "TrueFactSuggestedLineBreak": "在水面上漂浮的小冰山\r被称为“飘浮冰山”。",
    "FalseFactEnglish": "A mass of floating ice that looks like an iceberg is called a Popsicberg.",
    "FalseFactMandarin": "在水面上漂浮的小冰山被称为“飘浮冰山”。",
    "TrueFactSpanish": "Una masa de hielo flotante que parece un iceberg se denomina floeberg.",
    "FalseFactSpanish": "Una masa de hielo flotante que parece un iceberg se denomina Popsicberg."
  },
  {
    "TrueFactEnglish": "A newborn blue whale can be longer than an adult elephant.",
    "TrueFactMandarin": "蓝鲸宝宝的体积比一头成年大象还要大。",
    "TrueFactSuggestedLineBreak": "蓝鲸宝宝的体积\r比一只成年狗还要小。",
    "FalseFactEnglish": "A newborn blue whale is smaller than the average dog.",
    "FalseFactMandarin": "蓝鲸宝宝的体积比一只成年狗还要小。",
    "TrueFactSpanish": "Una ballena azul recién nacida puede ser más grande que un elefante adulto.",
    "FalseFactSpanish": "Una ballena azul recién nacida es más pequeña que un perro promedio."
  },
  {
    "TrueFactEnglish": "A sailfish can leap through the air at 68 miles an hour.",
    "TrueFactMandarin": "旗鱼能以每小时109公里的速度划过空中。",
    "TrueFactSuggestedLineBreak": "旗鱼能以每小时约13公里的速度\r划过空中。",
    "FalseFactEnglish": "A sailfish can leap through the air at 8 miles an hour.",
    "FalseFactMandarin": "旗鱼能以每小时约13公里的速度划过空中。",
    "TrueFactSpanish": "El pez vela puede saltar en el aire a 109.43 kilómetros por hora.",
    "FalseFactSpanish": "El pez vela puede saltar en el aire a 12.87 kilómetros por hora."
  },
  {
    "TrueFactEnglish": "A salmon’s sense of smell is hundreds of times better than a dog’s.",
    "TrueFactMandarin": "鲑鱼的嗅觉比狗的嗅觉敏感几百倍。",
    "TrueFactSuggestedLineBreak": "鲑鱼是唯一一种\r没有嗅觉的鱼类。",
    "FalseFactEnglish": "Salmon is the only type of fish with out a sense of smell.",
    "FalseFactMandarin": "鲑鱼是唯一一种没有嗅觉的鱼类。",
    "TrueFactSpanish": "El sentido del olfato de un salmón es cientos de veces más agudo que el de un perro.",
    "FalseFactSpanish": "El salmón es el único tipo de pez sin sentido de olfato."
  },
  {
    "TrueFactEnglish": "A seahorse can move its eyes in opposite directions.",
    "TrueFactMandarin": "海马的眼珠可以前后转动。",
    "TrueFactSuggestedLineBreak": "海马只能往前看。",
    "FalseFactEnglish": "A seahorse can only see what's directly in front of them.",
    "FalseFactMandarin": "海马只能往前看。",
    "TrueFactSpanish": "Un caballo de mar puede mover sus ojos en direcciones opuestas.",
    "FalseFactSpanish": "Un caballo de mar puede observar únicamente lo que tiene en frente de él."
  },
  {
    "TrueFactEnglish": "A shark can detect a fish’s heartbeat before it attacks.",
    "TrueFactMandarin": "鲨鱼展开攻击前可探测到猎物的心跳。",
    "TrueFactSuggestedLineBreak": "鲨鱼展开攻击前\r可探测到猎物的年龄。",
    "FalseFactEnglish": "A shark can detect a fish’s age before it attacks.",
    "FalseFactMandarin": "鲨鱼展开攻击前可探测到猎物的年龄。",
    "TrueFactSpanish": "Un tiburón puede detectar el latido del corazón de un pez antes de atacarlo.",
    "FalseFactSpanish": "Un tiburón puede detectar la edad de un pez antes de atacarlo."
  },
  {
    "TrueFactEnglish": "A shark can grow and lose up to 30,000 teeth in its lifetime.",
    "TrueFactMandarin": "鲨鱼一生能长出和掉落三万颗牙齿。",
    "TrueFactSuggestedLineBreak": "鲨鱼的牙齿永远不会脱落。",
    "FalseFactEnglish": "Sharks don't lose their teeth",
    "FalseFactMandarin": "鲨鱼的牙齿永远不会脱落。",
    "TrueFactSpanish": "Un tiburón puede desarrollar y perder hasta 30,000 dientes en su vida.",
    "FalseFactSpanish": "Los tiburones no pierden los dientes."
  },
  {
    "TrueFactEnglish": "A shark can live for six weeks without eating.",
    "TrueFactMandarin": "鲨鱼即使不进食也能存活六个星期。",
    "TrueFactSuggestedLineBreak": "鲨鱼每17个小时后\r就必须进食。",
    "FalseFactEnglish": "A shark needs to eat food once every 17 hours.",
    "FalseFactMandarin": "鲨鱼每17个小时后就必须进食。",
    "TrueFactSpanish": "Un tiburón puede vivir seis semanas sin comer.",
    "FalseFactSpanish": "Un tiburón necesita comer una vez cada 17 horas."
  },
  {
    "TrueFactEnglish": "A turtle’s shell is made up of about 50 bones.",
    "TrueFactMandarin": "龟壳里共有50根骨头。",
    "TrueFactSuggestedLineBreak": "龟壳里有一根骨头。",
    "FalseFactEnglish": "A turtle’s shell is made up of 1 bone.",
    "FalseFactMandarin": "龟壳里有一根骨头。",
    "TrueFactSpanish": "El caparazón de una tortuga está constituido de aproximadamente 50 huesos.",
    "FalseFactSpanish": "El caparazón de una tortuga está constituido de 1 hueso."
  },
  {
    "TrueFactEnglish": "A whale’s earwax can be as thick as a mattress.",
    "TrueFactMandarin": "鲸鱼的耳垢可能跟床褥一样厚。",
    "TrueFactSuggestedLineBreak": "鲸鱼是唯一一种\r不会长耳垢的哺乳动物。",
    "FalseFactEnglish": "Whales are the only mammal without ear wax.",
    "FalseFactMandarin": "鲸鱼是唯一一种不会长耳垢的哺乳动物。",
    "TrueFactSpanish": "La cerilla de una ballena puede ser tan grueso como un colchón.",
    "FalseFactSpanish": "Las ballenas son el único mamífero sin cerilla"
  },
  {
    "TrueFactEnglish": "All clownfish are born male.",
    "TrueFactMandarin": "刚出生的小丑鱼都是雄性的。",
    "TrueFactSuggestedLineBreak": "刚出生的小丑鱼都是雌性的。",
    "FalseFactEnglish": "All clownfish are born female.",
    "FalseFactMandarin": "刚出生的小丑鱼都是雌性的。",
    "TrueFactSpanish": "Todos los peces payaso nacen machos.",
    "FalseFactSpanish": "Todos los peces payaso nacen hembras."
  },
  {
    "TrueFactEnglish": "An electric eel can produce a charge strong enough to stun a horse.",
    "TrueFactMandarin": "电鳗产生的电能足以电晕一匹马。",
    "TrueFactSuggestedLineBreak": "电鳗不会产生电流。",
    "FalseFactEnglish": "An electric eel doesn’t actually produce electricity.",
    "FalseFactMandarin": "电鳗不会产生电流。",
    "TrueFactSpanish": "Una anguila eléctrica puede producir una descarga lo suficientemente poderosa como para aturdir a un caballo.",
    "FalseFactSpanish": "En realidad, una anguila eléctrica no produce electricidad."
  },
  {
    "TrueFactEnglish": "An octopus can detach an arm on purpose to distract a predator.",
    "TrueFactMandarin": "章鱼可通过断臂分散敌人的注意力。",
    "TrueFactSuggestedLineBreak": "锤头鲨可自断鱼鳍，\r以分散敌人的注意力。",
    "FalseFactEnglish": "Hammerhead sharks can detach their fins on purpose to distract predators.",
    "FalseFactMandarin": "锤头鲨可自断鱼鳍，以分散敌人的注意力。",
    "TrueFactSpanish": "Un pulpo puede desprenderse un brazo a propósito para distraer a un depredador.",
    "FalseFactSpanish": "Los tiburones martillo pueden desprender sus aletas a propósito para distraer a los depredadores."
  },
  {
    "TrueFactEnglish": "Certain sharks walk on their fins underwater.",
    "TrueFactMandarin": "有的鲨鱼会利用鱼鳍在海底下“行走”。",
    "TrueFactSuggestedLineBreak": "有的鲨鱼会利用鱼鳍\r将猎物抛来抛去，\r就跟我们玩抛球游戏一样。",
    "FalseFactEnglish": "Certain sharks use their fins for throwing fish back and forth like humans playing catch.",
    "FalseFactMandarin": "有的鲨鱼会利用鱼鳍将猎物抛来抛去，就跟我们玩抛球游戏一样。",
    "TrueFactSpanish": "Algunos tiburones caminan sobre sus aletas bajo el agua.",
    "FalseFactSpanish": "Algunos tiburones usan sus aletas para aventar peces como los humanos hacen con las pelotas."
  },
  {
    "TrueFactEnglish": "Chalk is made from the skeletons of ancient sea creatures.",
    "TrueFactMandarin": "粉笔是采用远古海洋生物的骨骼制成的。",
    "TrueFactSuggestedLineBreak": "粉笔是采用粉鱼的鳞片制成的。",
    "FalseFactEnglish": "Chalk is made from the scales of Chalkfish.",
    "FalseFactMandarin": "粉笔是采用粉鱼的鳞片制成的。",
    "TrueFactSpanish": "La tiza se elabora a partir de los esqueletos de criaturas marinas antiguas.",
    "FalseFactSpanish": "La tiza se elabora a partir de escamas de pez tiza."
  },
  {
    "TrueFactEnglish": "Crabs are distant relatives of spiders.",
    "TrueFactMandarin": "螃蟹和蜘蛛的远亲。",
    "TrueFactSuggestedLineBreak": "螃蟹和海龟的远亲。",
    "FalseFactEnglish": "Crabs are distant relatives of sea turtles.",
    "FalseFactMandarin": "螃蟹和海龟的远亲。",
    "TrueFactSpanish": "Los cangrejos son parientes lejanos de las arañas.",
    "FalseFactSpanish": "Los cangrejos son parientes lejanos de las tortugas marinas."
  },
  {
    "TrueFactEnglish": "Detached sea star arms sometimes grow new bodies.",
    "TrueFactMandarin": "被切断的海星臂有时会生出新的海星。",
    "TrueFactSuggestedLineBreak": "被切断的海星臂\r将成为海床表面的一部分。",
    "FalseFactEnglish": "All detached sea star arms become part of the ocean floor. ",
    "FalseFactMandarin": "被切断的海星臂将成为海床表面的一部分。",
    "TrueFactSpanish": "En ocasiones, las puntas desprendidas de las estrellas de mar desarrollan nuevos cuerpos.",
    "FalseFactSpanish": "Todas las puntas desprendidas de las estrellas de mar forman parte del lecho marino. "
  },
  {
    "TrueFactEnglish": "Dolphins can hear sounds underwater that are 15 miles away.",
    "TrueFactMandarin": "海豚可以听到水底下24公里以外的声音。",
    "TrueFactSuggestedLineBreak": "海豚只能在浮出水面后\r听见声音。",
    "FalseFactEnglish": "Dolphins can only hear above water.",
    "FalseFactMandarin": "海豚只能在浮出水面后听见声音。",
    "TrueFactSpanish": "Los delfines pueden escuchar sonidos bajo el agua que están a 24.14016 kilómetros de distancia.",
    "FalseFactSpanish": "Los delfines pueden escuchar únicamente por encima del agua."
  },
  {
    "TrueFactEnglish": "Eels can swim backwards.",
    "TrueFactMandarin": "鳗鱼可以后退。",
    "TrueFactSuggestedLineBreak": "鲨鱼可以后退。",
    "FalseFactEnglish": " Sharks can swim backwards.",
    "FalseFactMandarin": "鲨鱼可以后退。",
    "TrueFactSpanish": "Las anguilas pueden nadar hacia atrás.",
    "FalseFactSpanish": " Los tiburones pueden nadar hacia atrás."
  },
  {
    "TrueFactEnglish": "Fish can’t close their eyes.",
    "TrueFactMandarin": "鱼儿无法闭上双眼。",
    "TrueFactSuggestedLineBreak": "鱼儿睡觉时会闭上眼睛。",
    "FalseFactEnglish": "Fish sleep with their eyes closed.",
    "FalseFactMandarin": "鱼儿睡觉时会闭上眼睛。",
    "TrueFactSpanish": "Los peces no pueden cerrar los ojos.",
    "FalseFactSpanish": "Los peces duermen con los ojos cerrados."
  },
  {
    "TrueFactEnglish": "Hammerhead sharks can give birth to 40 babies at once.",
    "TrueFactMandarin": "锤头鲨一次能生下40个宝宝。",
    "TrueFactSuggestedLineBreak": "锤头鲨是孪生动物。",
    "FalseFactEnglish": "Hammerhead sharks lay eggs.",
    "FalseFactMandarin": "锤头鲨是孪生动物。",
    "TrueFactSpanish": "Los tiburones martillo pueden parir a 40 crías a la vez.",
    "FalseFactSpanish": "Los tiburones martillo ponen huevos."
  },
  {
    "TrueFactEnglish": "Herring communicate by passing gas.",
    "TrueFactMandarin": "鲱鱼通过放屁跟同伴沟通。",
    "TrueFactSuggestedLineBreak": "鲱鱼通过吐泡泡的方式\r跟同伴沟通。",
    "FalseFactEnglish": "Herring communicate by blowing bubbles with their mouths.",
    "FalseFactMandarin": "鲱鱼通过吐泡泡的方式跟同伴沟通。",
    "TrueFactSpanish": "Los arenques se comunican emitiendo gas.",
    "FalseFactSpanish": "Los arenques se comunican formando burbujas con sus bocas."
  },
  {
    "TrueFactEnglish": "Horseshoe crabs lived before dinosaurs.",
    "TrueFactMandarin": "马蹄蟹在恐龙出现之前就已经存在了。",
    "TrueFactSuggestedLineBreak": "马蹄蟹在地球上\r生存2000年了。",
    "FalseFactEnglish": "Horseshoe crabs have lived on this earth for 2000 years.",
    "FalseFactMandarin": "马蹄蟹在地球上生存2000年了。",
    "TrueFactSpanish": "Los cangrejos herradura vivieron antes de los dinosaurios.",
    "FalseFactSpanish": "Los cangrejos herradura han vivido en el planeta tierra durante 2000 años."
  },
  {
    "TrueFactEnglish": "If the longest blue whale could stand on its tail, it would be as tall as a ten-story building.",
    "TrueFactMandarin": "世上体积最长的蓝鲸站立起来，高度可达十层楼。",
    "TrueFactSuggestedLineBreak": "世上体积最长的蓝鲸站立起来，\r等于7辆汽车层层叠起的高度。",
    "FalseFactEnglish": "If the longest blue whale could stand on its tail, it would be as tall as a 7 cars stacked on top of each other.",
    "FalseFactMandarin": "世上体积最长的蓝鲸站立起来，等于7辆汽车层层叠起的高度。",
    "TrueFactSpanish": "Si la ballena azul más grande pudiera pararse sobre su cola, sería tan alta como un edificio de diez pisos. ",
    "FalseFactSpanish": "Si la ballena azul más grande pudiera pararse sobre su cola, sería tan grande como 7 automóviles apilados unos encima de otros. "
  },
  {
    "TrueFactEnglish": "It takes three liters of fresh water to make one liter of bottled water.",
    "TrueFactMandarin": "生产一公升的瓶装饮用水,需要用上三公升的淡水。",
    "TrueFactSuggestedLineBreak": "生产一公升的瓶装饮用水，\r需要用上九公升的淡水。",
    "FalseFactEnglish": "It takes 9 liters of fresh water to make one liter of bottled water.",
    "FalseFactMandarin": "生产一公升的瓶装饮用水，需要用上九公升的淡水。",
    "TrueFactSpanish": "Utilizamos tres litros de agua fresca para producir un litro de agua embotellada.",
    "FalseFactSpanish": "Toma 9 litros de agua fresca producir un litro de agua embotellada."
  },
  {
    "TrueFactEnglish": "It’s impossible for a person to sink in the Dead Sea.",
    "TrueFactMandarin": "在死海里，人永远不会沉没。",
    "TrueFactSuggestedLineBreak": "在死海里，人沉没得更快。",
    "FalseFactEnglish": "People sink in the Dead Sea faster than any other body of water.",
    "FalseFactMandarin": "在死海里，人沉没得更快。",
    "TrueFactSpanish": "Es imposible que una persona se hunda en el Mar Muerto.",
    "FalseFactSpanish": "Las personas se hunden en el Mar Muerto más rápido que en cualquier otro cuerpo de agua."
  },
  {
    "TrueFactEnglish": "Jellyfish can sting even when dead.",
    "TrueFactMandarin": "水母死后还可以蜇伤敌人。",
    "TrueFactSuggestedLineBreak": "水母死后，也就失去了毒性。",
    "FalseFactEnglish": "Once dead, a jelly fish loses it's sting.",
    "FalseFactMandarin": "水母死后，也就失去了毒性。",
    "TrueFactSpanish": "Las medusas pueden picar incluso cuando mueren.",
    "FalseFactSpanish": "Una vez que mueren, las medusas pierden su aguijón."
  },
  {
    "TrueFactEnglish": "Killer whales are actually dolphins.",
    "TrueFactMandarin": "杀人鲸和海豚是同类。",
    "TrueFactSuggestedLineBreak": "杀人鲸和食人鲨是同类。",
    "FalseFactEnglish": "Killer whales are actually Killer Sharks.",
    "FalseFactMandarin": "杀人鲸和食人鲨是同类。",
    "TrueFactSpanish": "Las ballenas asesinas son en realidad delfines.",
    "FalseFactSpanish": "Las ballenas asesinas son en realidad tiburones asesinos."
  },
  {
    "TrueFactEnglish": "Lobsters can regrow missing claws.",
    "TrueFactMandarin": "龙虾的钳子断了会重新长出来。",
    "TrueFactSuggestedLineBreak": "鲨鱼的背鳍断了\r会重新长出来。",
    "FalseFactEnglish": "Sharks can regrow missing fins.",
    "FalseFactMandarin": "鲨鱼的背鳍断了会重新长出来。",
    "TrueFactSpanish": "Las langostas pueden regenerar tenazas faltantes.",
    "FalseFactSpanish": "Los tiburones pueden regenerar aletas faltantes."
  },
  {
    "TrueFactEnglish": "More water is in the pacific ocean than in all of the other seas and oceans combined.",
    "TrueFactMandarin": "将所有海洋的水量凑合起来，仍然不及太平洋的水量。",
    "TrueFactSuggestedLineBreak": "大西洋的面积\r比太平洋还要大。",
    "FalseFactEnglish": "The Atlantic Ocean is larger than the Pacific Ocean.",
    "FalseFactMandarin": "大西洋的面积比太平洋还要大。",
    "TrueFactSpanish": "Existe más agua en el océano pacífico que en cualquier otro mar u océano combinados.",
    "FalseFactSpanish": "El Océano Atlántico es más grande que el Océano Pacífico."
  },
  {
    "TrueFactEnglish": "Most sharks would sink in freshwater.",
    "TrueFactMandarin": "大部分鲨鱼在淡水中会往下沉。",
    "TrueFactSuggestedLineBreak": "大部分鲨鱼\r无法在淡水深处中潜游。",
    "FalseFactEnglish": "Most sharks can not dive deep in freshwater.",
    "FalseFactMandarin": "大部分鲨鱼无法在淡水深处中潜游。",
    "TrueFactSpanish": "La mayoría de los tiburones se hundirían en agua dulce.",
    "FalseFactSpanish": "La mayoría de los tiburones no pueden sumergirse profundamente en agua dulce."
  },
  {
    "TrueFactEnglish": "Most squids have three hearts.",
    "TrueFactMandarin": "大部分墨鱼有三个心脏。",
    "TrueFactSuggestedLineBreak": "大部分墨鱼有三个胃。",
    "FalseFactEnglish": "Squids have three stomaches.",
    "FalseFactMandarin": "大部分墨鱼有三个胃。",
    "TrueFactSpanish": "La mayoría de los calamares tienen tres corazones.",
    "FalseFactSpanish": "Los calamares tienen tres estómagos."
  },
  {
    "TrueFactEnglish": "One teaspoon of seawater contains five million living organisms.",
    "TrueFactMandarin": "一茶匙的海水含有五百万个活生物。",
    "TrueFactSuggestedLineBreak": "一茶匙的海水\r含有一百万个活生物。",
    "FalseFactEnglish": "One teaspoon of seawater contains almost 1 million living organisms.",
    "FalseFactMandarin": "一茶匙的海水含有一百万个活生物。",
    "TrueFactSpanish": "Una cucharada de agua de mar contiene cinco millones de organismos vivientes.",
    "FalseFactSpanish": "Una cucharada de agua de mar contiene casi 1 millón de organismos vivientes."
  },
  {
    "TrueFactEnglish": "Oysters change from male to female.",
    "TrueFactMandarin": "牡蛎可从雄性变成雌性。",
    "TrueFactSuggestedLineBreak": "牡蛎都是雌性的。",
    "FalseFactEnglish": "All Oysters are female",
    "FalseFactMandarin": "牡蛎都是雌性的。",
    "TrueFactSpanish": "Las ostras cambian de macho a hembra.",
    "FalseFactSpanish": "Todas las ostras son hembras."
  },
  {
    "TrueFactEnglish": "Parrotfish sleep in cocoons of their own mucus.",
    "TrueFactMandarin": "鹦哥鱼睡在沾满自己粘液的茧。",
    "TrueFactSuggestedLineBreak": "鹦哥鱼的窝巢\r就跟鹦鹉的窝巢一样。",
    "FalseFactEnglish": "Parrotfish sleep in nests like parrot birds.",
    "FalseFactMandarin": "鹦哥鱼的窝巢就跟鹦鹉的窝巢一样。",
    "TrueFactSpanish": "Los peces loro, duermen en capullos hechos de su propia mucosa.",
    "FalseFactSpanish": "Los peces loro, duermen en nidos como loros."
  },
  {
    "TrueFactEnglish": "Sarcastic fringehead fish battle over turf by wrestling each other with their mouths.",
    "TrueFactMandarin": "为了争取地盘，勃氏新热鳚会把口大大张开与对手打斗。",
    "TrueFactSuggestedLineBreak": "为了争取地盘，\r勃氏新热鳚会将石子和海藻\r当成是武器来攻击对手。",
    "FalseFactEnglish": "Sarcastic fringehead fish battle over turf by using weopons such as stones and seaweed.",
    "FalseFactMandarin": "为了争取地盘，勃氏新热鳚会将石子和海藻当成是武器来攻击对手。",
    "TrueFactSpanish": "Los tubícolas chuscos luchan por un territorio luchando con sus bocas.",
    "FalseFactSpanish": "Los tubícolas chuscos luchan por territorio usando piedras y algas marinas como armas"
  },
  {
    "TrueFactEnglish": "Scientists think sharks are color-blind.",
    "TrueFactMandarin": "科学家认为鲨鱼患有色盲。",
    "TrueFactSuggestedLineBreak": "科学家认为，\r鲨鱼看到的颜色比人类还要多。",
    "FalseFactEnglish": "Scientists think sharks can see more colors than a human.",
    "FalseFactMandarin": "科学家认为，鲨鱼看到的颜色比人类还要多。",
    "TrueFactSpanish": "Los científicos creen que los tiburones son daltónicos.",
    "FalseFactSpanish": "Los científicos creen que los tiburones perciben más colores que los seres humanos."
  },
  {
    "TrueFactEnglish": "Sea snail mucus was once used to make purple dye.",
    "TrueFactMandarin": "曾经有人用海螺的粘液来制造紫色颜料。",
    "TrueFactSuggestedLineBreak": "曾经有人用海螺的粘液\r来制造雨伞。",
    "FalseFactEnglish": "Sea snail mucus was once used to make umbrellas.",
    "FalseFactMandarin": "曾经有人用海螺的粘液来制造雨伞。",
    "TrueFactSpanish": "El moco del caracol de mar se usaba para elaborar un tinte color morado.",
    "FalseFactSpanish": "El moco del caracol de mar se usaba para elaborar paraguas."
  },
  {
    "TrueFactEnglish": "Seahorses do not have stomachs.",
    "TrueFactMandarin": "海马没有胃。",
    "TrueFactSuggestedLineBreak": "海马有两个胃。",
    "FalseFactEnglish": "Seahorses have 2 stomachs.",
    "FalseFactMandarin": "海马有两个胃。",
    "TrueFactSpanish": "Los caballos de mar no tienen estómagos.",
    "FalseFactSpanish": "Los caballos de mar tienen 2 estómagos."
  },
  {
    "TrueFactEnglish": "Sharks are older than trees.",
    "TrueFactMandarin": "鲨鱼的寿命比树还长。",
    "TrueFactSuggestedLineBreak": "鲨鱼是地球上最年轻的物种。",
    "FalseFactEnglish": "Sharks are some of the youngest creatures on this planet.",
    "FalseFactMandarin": "鲨鱼是地球上最年轻的物种。",
    "TrueFactSpanish": "Los tiburones son más viejos que los árboles.",
    "FalseFactSpanish": "Los tiburones son unas de las criaturas más jóvenes en este planeta."
  },
  {
    "TrueFactEnglish": "Sharks have eight senses. Humans have only five.",
    "TrueFactMandarin": "鲨鱼有8个感官，而人只有5个感官。",
    "TrueFactSuggestedLineBreak": "鲨鱼的感官比人类还要少。",
    "FalseFactEnglish": "Sharks have less senses than humans do.",
    "FalseFactMandarin": "鲨鱼的感官比人类还要少。",
    "TrueFactSpanish": "Los tiburones tienen ocho sentidos. Los humanos tienen solamente cinco.",
    "FalseFactSpanish": "Los tiburones tienen menos sentidos que los humanos."
  },
  {
    "TrueFactEnglish": "Sharks have no bones.",
    "TrueFactMandarin": "鲨鱼全身上下没有任何骨头。",
    "TrueFactSuggestedLineBreak": "鲨鱼全身上下\r比人类多出14根骨头。",
    "FalseFactEnglish": "Sharks have 14 more bones than the average human.",
    "FalseFactMandarin": "鲨鱼全身上下比人类多出14根骨头。",
    "TrueFactSpanish": "Los tiburones no tienen huesos.",
    "FalseFactSpanish": "Los tiburones tienen 14 huesos más que las personas promedio."
  },
  {
    "TrueFactEnglish": "Some clams live to be more than a hundred years old.",
    "TrueFactMandarin": "有的蛤蜊可活上一百多岁。",
    "TrueFactSuggestedLineBreak": "蛤蜊不能活上45年。",
    "FalseFactEnglish": "Clams do not live past 45 years.",
    "FalseFactMandarin": "蛤蜊不能活上45年。",
    "TrueFactSpanish": "Algunas almejas viven más de cien años.",
    "FalseFactSpanish": "Las almejas no viven más de 45 años."
  },
  {
    "TrueFactEnglish": "Some fish can change from female to male.",
    "TrueFactMandarin": "有的鱼可以从雌性变成雄性。",
    "TrueFactSuggestedLineBreak": "所有鱼类都无法变性。",
    "FalseFactEnglish": "Once is fish is born a male, it stays that way.",
    "FalseFactMandarin": "所有鱼类都无法变性。",
    "TrueFactSpanish": "Algunos peces pueden cambiar de hembra a macho.",
    "FalseFactSpanish": "Una vez que el pez nace macho se queda de esa manera."
  },
  {
    "TrueFactEnglish": "Some fish can taste with their tails.",
    "TrueFactMandarin": "有的鱼类的尾巴含有味蕾，使它们能用尾巴尝味。",
    "TrueFactSuggestedLineBreak": "鱼没有味蕾。",
    "FalseFactEnglish": "Fish don't have taste buds.",
    "FalseFactMandarin": "鱼没有味蕾。",
    "TrueFactSpanish": "Algunos peces pueden percibir sabor con sus colas.",
    "FalseFactSpanish": "Los peces no tienen papilas gustativas."
  },
  {
    "TrueFactEnglish": "Some fish can walk on land.",
    "TrueFactMandarin": "有的鱼类可以在陆地上行走。",
    "TrueFactSuggestedLineBreak": "有的海马可以在陆地上行走。",
    "FalseFactEnglish": "Some seahorses can walk on land.",
    "FalseFactMandarin": "有的海马可以在陆地上行走。",
    "TrueFactSpanish": "Algunos peces pueden caminar en la tierra.",
    "FalseFactSpanish": "Algunos caballos de mar pueden caminar en la tierra."
  },
  {
    "TrueFactEnglish": "Some fish use their fins to “walk” along the ocean floor.",
    "TrueFactMandarin": "有的鱼会使用鳍在海底下“走动”。",
    "TrueFactSuggestedLineBreak": "有的鱼会使用鳍去戏弄同伴。",
    "FalseFactEnglish": "Some fish use their fins to jester to other fish.",
    "FalseFactMandarin": "有的鱼会使用鳍去戏弄同伴。",
    "TrueFactSpanish": "Algunos peces usan sus aletas para \"caminar\" en el lecho marino.",
    "FalseFactSpanish": "Algunos peces usan sus aletas para hacer bromas a otros peces."
  },
  {
    "TrueFactEnglish": "Some lobsters are electric blue.",
    "TrueFactMandarin": "有的龙虾是铁蓝色的。",
    "TrueFactSuggestedLineBreak": "龙虾都是红色的。",
    "FalseFactEnglish": "Lobsters are all some shade of red.",
    "FalseFactMandarin": "龙虾都是红色的。",
    "TrueFactSpanish": "Algunas langostas son azul eléctrico.",
    "FalseFactSpanish": "Todas las langostas son de algún tono de rojo."
  },
  {
    "TrueFactEnglish": "Some sand dunes bark.",
    "TrueFactMandarin": "沙丘会发出吠叫声。",
    "TrueFactSuggestedLineBreak": "沙丘会发出\r类似鸭子的呱呱叫声。",
    "FalseFactEnglish": "Some sand dunes quack like a duck.",
    "FalseFactMandarin": "沙丘会发出类似鸭子的呱呱叫声。",
    "TrueFactSpanish": "Algunas dunas de arena ladran.",
    "FalseFactSpanish": "Algunas dunas de arena graznan como patos."
  },
  {
    "TrueFactEnglish": "Some sharks can live to be 75 years old.",
    "TrueFactMandarin": "有些鲨鱼能活上75年。",
    "TrueFactSuggestedLineBreak": "海马能活上75年。",
    "FalseFactEnglish": "Seahorses can live to be 75 years old.",
    "FalseFactMandarin": "海马能活上75年。",
    "TrueFactSpanish": "Algunos tiburones pueden vivir hasta 75 años.",
    "FalseFactSpanish": "Los caballos de mar pueden vivir hasta los 75 años."
  },
  {
    "TrueFactEnglish": "Some squat lobsters—a kind of crustacean—are covered in hairlike bristles.",
    "TrueFactMandarin": "铠甲虾是一种甲壳类动物；有些铠甲虾身上布满鬃毛。",
    "TrueFactSuggestedLineBreak": "铠甲虾是一种甲壳类动物；\r有些铠甲虾身上布满奇石。",
    "FalseFactEnglish": "Some squat lobsters—a kind of crustacean—are covered in rare jewels.",
    "FalseFactMandarin": "铠甲虾是一种甲壳类动物；有些铠甲虾身上布满奇石。",
    "TrueFactSpanish": "Algunos langostinos -una especie de crustáceo- están cubiertos en cerdas parecidas al pelo.",
    "FalseFactSpanish": "Algunos langostinos -una especie de crustáceo- están cubiertos de joyas raras."
  },
  {
    "TrueFactEnglish": "Sperm whales have the heaviest brains on the planet.",
    "TrueFactMandarin": "抹香鲸拥有地球上最重的脑袋。",
    "TrueFactSuggestedLineBreak": "大白鲨拥有地球上\r所有生物中最重的脑袋。",
    "FalseFactEnglish": "Great White Sharks have the heaviest brains on the planet.",
    "FalseFactMandarin": "大白鲨拥有地球上所有生物中最重的脑袋。",
    "TrueFactSpanish": "Los cachalotes tienen los cerebros más pesados en el planeta.",
    "FalseFactSpanish": "Los tiburones blancos tienen los cerebros más pesados en el planeta."
  },
  {
    "TrueFactEnglish": "Swarms of jellyfish stretching 100 miles have appeared in the Gulf of Mexico.",
    "TrueFactMandarin": "墨西哥湾曾经出现160公里长的水母群。",
    "TrueFactSuggestedLineBreak": "墨西哥湾曾经出现\r160公里长的座头鲸群。",
    "FalseFactEnglish": "Swarms of humpback whales stretching 100 miles have appeared in the Gulf of Mexico.",
    "FalseFactMandarin": "墨西哥湾曾经出现160公里长的座头鲸群。",
    "TrueFactSpanish": "En el Golfo de México se han observado flores de medusas que abarcan 160.93 kilómetros.",
    "FalseFactSpanish": "En el Golfo de México se han observado ballenas jorobadas que abarcan los 160.934 kilómetros."
  },
  {
    "TrueFactEnglish": "The Dead Sea is seven times saltier than any ocean.",
    "TrueFactMandarin": "死海的咸度比任何海洋高上7倍。",
    "TrueFactSuggestedLineBreak": "死海是世界上\r最大的淡水源地。",
    "FalseFactEnglish": "The Dead Sea is the largest fresh water resource.",
    "FalseFactMandarin": "死海是世界上最大的淡水源地。",
    "TrueFactSpanish": "El Mar Muerto es siete veces más salado que cualquier océano.",
    "FalseFactSpanish": "El Mar Muerto es la fuente de agua dulce más grande."
  },
  {
    "TrueFactEnglish": "The largest known octopus had arms long enough to wrap around four cars.",
    "TrueFactMandarin": "世上体积最大的章鱼的胳膊足以缠住四辆轿车。",
    "TrueFactSuggestedLineBreak": "世上体积最大的海星，\r其胳膊足以缠住四辆轿车。",
    "FalseFactEnglish": "The largest known star fish had arms long enough to wrap around four cars.",
    "FalseFactMandarin": "世上体积最大的海星，其胳膊足以缠住四辆轿车。",
    "TrueFactSpanish": "El pulpo más grande conocido tenía brazos lo suficientemente largos para abarcar cuatro automóviles.",
    "FalseFactSpanish": "La estrella de mar más grande conocida tenía brazos lo suficientemente largos como para abarcar cuatro automóviles."
  },
  {
    "TrueFactEnglish": "The male killer whale’s dorsal (back) fin is almost six feet high—the height of a tall man.",
    "TrueFactMandarin": "雄性杀人鲸的背鳍可高达183厘米，高度相等于一个身材高大的男人。",
    "TrueFactSuggestedLineBreak": "雄性杀人鲸没有背鳍，\r而雌性杀人鲸则长有背鳍。",
    "FalseFactEnglish": "Unlike female killer whales, a male killer whale doesn't have a dorsal (back) fin. ",
    "FalseFactMandarin": "雄性杀人鲸没有背鳍，而雌性杀人鲸则长有背鳍。",
    "TrueFactSpanish": "La aleta dorsal (trasera) de una ballena asesina macho tiene una altura aproximada de 1.82 metros - la altura de un hombre alto.",
    "FalseFactSpanish": "A diferencia de las ballenas asesinas hembra, la ballena asesina macho no tiene una aleta dorsal (trasera). "
  },
  {
    "TrueFactEnglish": "The sound of an iceberg breaking is louder than 214 oil tanker engines.",
    "TrueFactMandarin": "冰山崩塌发出的声响比214台油箱发动机同时操作发出的声响来得更大声。",
    "TrueFactSuggestedLineBreak": "冰山崩塌时，\r海面上一片宁静。",
    "FalseFactEnglish": "An iceberg breaking is the quietest sound in the ocean.",
    "FalseFactMandarin": "冰山崩塌时，海面上一片宁静。",
    "TrueFactSpanish": "El sonido de la ruptura de un Iceberg es más fuerte que 214 motores de barcos petroleros.",
    "FalseFactSpanish": "La ruptura de un iceberg es el sonido más silencioso en el mar."
  },
  {
    "TrueFactEnglish": "The sound of waves crashing comes mostly from bubbles.",
    "TrueFactMandarin": "海浪的滔滔声响，很多时候是泡沫溢出的声音。",
    "TrueFactSuggestedLineBreak": "海浪的滔滔声响，\r很多时候是鱼儿游过的声音。",
    "FalseFactEnglish": "The sound of waves crashing comes from fish passing gas.",
    "FalseFactMandarin": "海浪的滔滔声响，很多时候是鱼儿游过的声音。",
    "TrueFactSpanish": "El sonido de olas chocando proviene principalmente de las burbujas.",
    "FalseFactSpanish": "El sonido de las olas chocando proviene de los peces emitiendo gas."
  },
  {
    "TrueFactEnglish": "The Titanic was held together by 3 million rivets.",
    "TrueFactMandarin": "铁达尼号由三百万支铆钉固定。",
    "TrueFactSuggestedLineBreak": "铁达尼号由五十万支铆钉固定。",
    "FalseFactEnglish": "The Titanic was held together by 500,000 rivets.",
    "FalseFactMandarin": "铁达尼号由五十万支铆钉固定。",
    "TrueFactSpanish": "El Titanic permanecía unido por 3 millones de remaches.",
    "FalseFactSpanish": "El Titanic permanecía unido por 500,000  remaches."
  },
  {
    "TrueFactEnglish": "The world’s oceans contain enough gold to give two pounds to every person on the planet.",
    "TrueFactMandarin": "如果能将海洋所含有的金矿平分给地球上的每个人，每人可分得1.8斤的黄金。",
    "TrueFactSuggestedLineBreak": "海洋所含有的金矿\r可制造成1000枚戒指。",
    "FalseFactEnglish": "The world’s oceans contain enough gold to make 1000 wedding rings.",
    "FalseFactMandarin": "海洋所含有的金矿可制造成1000枚戒指。",
    "TrueFactSpanish": "Los océanos del mundo contienen suficiente oro para que cada persona en el planeta pueda tener 0.907184 kilogramos. ",
    "FalseFactSpanish": "Los océanos del mundo contienen suficiente oro para elaborar 1000 anillos de boda."
  },
  {
    "TrueFactEnglish": "Various fish eggs hatch in the dad’s mouth.",
    "TrueFactMandarin": "有些鱼类的鱼卵在鱼爸爸的口中孵化。",
    "TrueFactSuggestedLineBreak": "鱼不是卵生动物。",
    "FalseFactEnglish": "Fish don't lay eggs.",
    "FalseFactMandarin": "鱼不是卵生动物。",
    "TrueFactSpanish": "Varios peces incuban sus huevos en la boca del macho.",
    "FalseFactSpanish": "Los peces no ponen huevos."
  },
  {
    "TrueFactEnglish": "Vinegar can dissolve pearls.",
    "TrueFactMandarin": "珍珠能被醋液溶解。",
    "TrueFactSuggestedLineBreak": "珍珠是无法被溶解的。",
    "FalseFactEnglish": "Pearls cannot be dissolved.",
    "FalseFactMandarin": "珍珠是无法被溶解的。",
    "TrueFactSpanish": "El vinagre puede disolver perlas.",
    "FalseFactSpanish": "Las perlas no se pueden disolver."
  },
  {
    "TrueFactEnglish": "Water blown out of a blue whale’s spout can shoot three stories high.",
    "TrueFactMandarin": "蓝鲸从它的喷口所喷出的水可达三层楼高。",
    "TrueFactSuggestedLineBreak": "蓝鲸从它的喷口\r所喷出的水可达约两米高。",
    "FalseFactEnglish": "Water blown out of a blue whale’s spout can shoot six feet high.",
    "FalseFactMandarin": "蓝鲸从它的喷口所喷出的水可达约两米高。",
    "TrueFactSpanish": "El agua expulsada del espiráculo de una ballena azul puede alcanzar tres pisos de altura.",
    "FalseFactSpanish": "El agua expulsada del espiráculo de una ballena azul puede alcanzar los 1.82 metros de altura."
  },
  {
    "TrueFactEnglish": "You can tell the age of some fish by counting the rings on their scales.",
    "TrueFactMandarin": "我们可以通过鱼的鳞片数量来预测到鱼的年龄。",
    "TrueFactSuggestedLineBreak": "我们可以从鱼的眼睛\r测出它的年龄。",
    "FalseFactEnglish": "You can tell the age of some fish by lookin into their eyes.",
    "FalseFactMandarin": "我们可以从鱼的眼睛测出它的年龄。",
    "TrueFactSpanish": "Se puede saber la edad de algunos peces al contar los anillos de sus escamas.",
    "FalseFactSpanish": "Se puede saber la edad de algunos peces mirando sus ojos."
  }
]
